simplhdl/__init__.py
simplhdl/__main__.py
simplhdl/cocotb.py
simplhdl/simplhdl.py
simplhdl/tools.py
simplhdl/utils.py
simplhdl/cli/arguments.py
simplhdl/cli/info.py
simplhdl/cli/run.py
simplhdl/plugin/__init__.py
simplhdl/plugin/flow.py
simplhdl/plugin/generator.py
simplhdl/plugin/implementationflow.py
simplhdl/plugin/loader.py
simplhdl/plugin/parser.py
simplhdl/plugin/simulationflow.py
simplhdl/project/__init__.py
simplhdl/project/attributes.py
simplhdl/project/base.py
simplhdl/project/design.py
simplhdl/project/files.py
simplhdl/project/fileset.py
simplhdl/project/project.py
simplhdl-0.10.0.dist-info/licenses/LICENSE
simplhdl_chisel/chisel.py
simplhdl_encrypt/__init__.py
simplhdl_encrypt/encrypt/__init__.py
simplhdl_encrypt/encrypt/encryptflow.py
simplhdl_fusesocparser/__init__.py
simplhdl_fusesocparser/fusesocparser.py
simplhdl_lint/__init__.py
simplhdl_lint/flake8/flake8flow.py
simplhdl_lint/lint/lintflow.py
simplhdl_lint/resources/__init__.py
simplhdl_lint/resources/templates/__init__.py
simplhdl_lint/resources/templates/flake8/__init__.py
simplhdl_lint/resources/templates/flake8/setup.cfg.j2
simplhdl_lint/resources/templates/verible/__init__.py
simplhdl_lint/resources/templates/verible/rules.cfg.j2
simplhdl_lint/resources/templates/vsg/__init__.py
simplhdl_lint/resources/templates/vsg/files.json.j2
simplhdl_lint/resources/templates/vsg/rules.yml.j2
simplhdl_lint/verible/__init__.py
simplhdl_lint/verible/veribleflow.py
simplhdl_lint/vsg/__init__.py
simplhdl_lint/vsg/vsgflow.py
simplhdl_modelsim/__init__.py
simplhdl_modelsim/modelsim/__init__.py
simplhdl_modelsim/modelsim/modelsimflow.py
simplhdl_modelsim/resources/__init__.py
simplhdl_modelsim/resources/templates/__init__.py
simplhdl_modelsim/resources/templates/modelsim/Makefile.j2
simplhdl_modelsim/resources/templates/modelsim/__init__.py
simplhdl_modelsim/resources/templates/modelsim/cocotb.mk.j2
simplhdl_modelsim/resources/templates/modelsim/dependencies.mk.j2
simplhdl_modelsim/resources/templates/modelsim/files.j2
simplhdl-0.10.0.dist-info/METADATA
simplhdl-0.10.0.dist-info/WHEEL
simplhdl-0.10.0.dist-info/entry_points.txt
simplhdl-0.10.0.dist-info/top_level.txt
simplhdl-0.10.0.dist-info/RECORD
