Metadata-Version: 2.4
Name: SimplHDL
Version: 0.10.0
Summary: A framework for simulating and implementing HDL designs
Author-email: Rasmus Grøndahl Olsen <simplhdl@gmail.com>
Maintainer-email: Rasmus Grøndahl Olsen <simplhdl@gmail.com>
License: MIT License
Project-URL: Homepage, https://github.com/SimplHDL
Project-URL: Documentation, https://simplhdl.readthedocs.io/en/latest/
Project-URL: Repository, https://github.com/SimplHDL/simplhdl.git
Project-URL: Issues, https://github.com/SimplHDL/simplhdl/issues
Classifier: Development Status :: 4 - Beta
Classifier: Programming Language :: Python :: 3
Classifier: Programming Language :: Python :: 3.8
Classifier: Programming Language :: Python :: 3.9
Classifier: Programming Language :: Python :: 3.10
Classifier: Programming Language :: Python :: 3.11
Classifier: Programming Language :: Python :: 3.12
Classifier: Programming Language :: Python :: 3.13
Classifier: Programming Language :: Python :: 3.14
Classifier: Intended Audience :: Developers
Classifier: License :: OSI Approved :: MIT License
Classifier: Operating System :: OS Independent
Requires-Python: >=3.8
License-File: LICENSE
Requires-Dist: argcomplete
Requires-Dist: black
Requires-Dist: flake8
Requires-Dist: GitPython
Requires-Dist: importlib-resources; python_version < "3.9"
Requires-Dist: jinja2
Requires-Dist: matplotlib
Requires-Dist: networkx
Requires-Dist: peakrdl-html
Requires-Dist: peakrdl-pyuvm
Requires-Dist: peakrdl-regblock>=1.2.0
Requires-Dist: pyyaml
Requires-Dist: rich
Requires-Dist: singleton-decorator
Requires-Dist: systemrdl-compiler
Requires-Dist: types-PyYAML
Requires-Dist: vsg
Provides-Extra: dev
Requires-Dist: flake8; extra == "dev"
Requires-Dist: mypy; extra == "dev"
Requires-Dist: robotframework; extra == "dev"
Requires-Dist: tox; extra == "dev"
Provides-Extra: docs
Requires-Dist: furo; extra == "docs"
Requires-Dist: Sphinx; extra == "docs"
Requires-Dist: sphinx_pyproject; extra == "docs"
Dynamic: license-file
